[
  { "nome": "Ceará", "taxa_frete": 8 },
  { "nome": "Piauí", "taxa_frete": 12 },
  { "nome": "Rio Grande do Norte", "taxa_frete": 12 },
  { "nome": "Paraíba", "taxa_frete": 12 },
  { "nome": "Pernambuco", "taxa_frete": 12 },
  { "nome": "Alagoas", "taxa_frete": 12 },
  { "nome": "Sergipe", "taxa_frete": 12 },
  { "nome": "Bahia", "taxa_frete": 15 },
  { "nome": "Maranhão", "taxa_frete": 18 },
  { "nome": "Amazonas", "taxa_frete": 25 },
  { "nome": "Roraima", "taxa_frete": 25 },
  { "nome": "Acre", "taxa_frete": 25 },
  { "nome": "Rondônia", "taxa_frete": 25 },
  { "nome": "Pará", "taxa_frete": 20 },
  { "nome": "Amapá", "taxa_frete": 20 },
  { "nome": "Tocantins", "taxa_frete": 18 },
  { "nome": "Goiás", "taxa_frete": 18 },
  { "nome": "Mato Grosso", "taxa_frete": 18 },
  { "nome": "Mato Grosso do Sul", "taxa_frete": 18 },
  { "nome": "Distrito Federal", "taxa_frete": 18 },
  { "nome": "São Paulo", "taxa_frete": 20 },
  { "nome": "Rio de Janeiro", "taxa_frete": 20 },
  { "nome": "Minas Gerais", "taxa_frete": 20 },
  { "nome": "Espírito Santo", "taxa_frete": 20 },
  { "nome": "Paraná", "taxa_frete": 22 },
  { "nome": "Santa Catarina", "taxa_frete": 22 },
  { "nome": "Rio Grande do Sul", "taxa_frete": 22 }
]
